casaplotms/plotms.py
casaplotms/LICENSE.txt
casaplotms/__init__.py
casaplotms/private/shutdown_pb2.py
casaplotms/private/plotmstool.py
casaplotms/private/shutdown_pb2_grpc.py
casaplotms/private/plotms_pb2_grpc.py
casaplotms/private/plotms_pb2.py
casaplotms/private/task_plotms.py
casaplotms/private/ping_pb2_grpc.py
casaplotms/private/ping_pb2.py
casaplotms/__bin__/casaplotms-x86_64.AppImage
casaplotms/gotasks/plotms.py
casaplotms/gotasks/__init__.py
casaplotms-2.7.4.dist-info/WHEEL
casaplotms-2.7.4.dist-info/RECORD
casaplotms-2.7.4.dist-info/top_level.txt
casaplotms-2.7.4.dist-info/METADATA
