Metadata-Version: 2.1
Name: casaplotms
Version: 2.7.4
Summary: UNKNOWN
Home-page: https://open-bitbucket.nrao.edu/projects/CASA/repos/casaplotms/browse
Author: CASA development team
Author-email: casa-feedback@nrao.edu
Maintainer: Darrell Schiebel
Maintainer-email: drs@nrao.edu
License: GNU Library or Lesser General Public License (LGPL)
Download-URL: https://casa.nrao.edu/download/
Platform: UNKNOWN
Requires-Dist: grpcio
Requires-Dist: protobuf
Requires-Dist: casatasks
